{
    "task": "LaMP_1",
    "golds": [
        {
            "id": "002489",
            "output": "[1]"
        },
        {
            "id": "007660",
            "output": "[1]"
        },
        {
            "id": "006115",
            "output": "[1]"
        },
        {
            "id": "005778",
            "output": "[1]"
        },
        {
            "id": "00287",
            "output": "[1]"
        },
        {
            "id": "003279",
            "output": "[1]"
        },
        {
            "id": "007338",
            "output": "[1]"
        },
        {
            "id": "001932",
            "output": "[1]"
        },
        {
            "id": "006167",
            "output": "[1]"
        },
        {
            "id": "009433",
            "output": "[1]"
        },
        {
            "id": "004168",
            "output": "[1]"
        },
        {
            "id": "004899",
            "output": "[1]"
        },
        {
            "id": "001994",
            "output": "[1]"
        },
        {
            "id": "0067",
            "output": "[1]"
        },
        {
            "id": "002220",
            "output": "[1]"
        },
        {
            "id": "004458",
            "output": "[1]"
        },
        {
            "id": "005789",
            "output": "[1]"
        },
        {
            "id": "008001",
            "output": "[1]"
        },
        {
            "id": "002744",
            "output": "[1]"
        },
        {
            "id": "003119",
            "output": "[1]"
        },
        {
            "id": "006882",
            "output": "[1]"
        },
        {
            "id": "006344",
            "output": "[1]"
        },
        {
            "id": "006817",
            "output": "[1]"
        },
        {
            "id": "008427",
            "output": "[1]"
        },
        {
            "id": "00832",
            "output": "[1]"
        },
        {
            "id": "001143",
            "output": "[1]"
        },
        {
            "id": "004702",
            "output": "[1]"
        },
        {
            "id": "005878",
            "output": "[1]"
        },
        {
            "id": "006255",
            "output": "[1]"
        },
        {
            "id": "002165",
            "output": "[1]"
        },
        {
            "id": "001257",
            "output": "[1]"
        },
        {
            "id": "008882",
            "output": "[1]"
        },
        {
            "id": "002264",
            "output": "[1]"
        },
        {
            "id": "00177",
            "output": "[1]"
        },
        {
            "id": "002685",
            "output": "[1]"
        },
        {
            "id": "004894",
            "output": "[1]"
        },
        {
            "id": "006055",
            "output": "[1]"
        },
        {
            "id": "007060",
            "output": "[1]"
        },
        {
            "id": "001333",
            "output": "[1]"
        },
        {
            "id": "004813",
            "output": "[1]"
        },
        {
            "id": "003030",
            "output": "[1]"
        },
        {
            "id": "006917",
            "output": "[1]"
        },
        {
            "id": "003410",
            "output": "[1]"
        },
        {
            "id": "007769",
            "output": "[1]"
        },
        {
            "id": "001799",
            "output": "[1]"
        },
        {
            "id": "009634",
            "output": "[1]"
        },
        {
            "id": "004931",
            "output": "[1]"
        },
        {
            "id": "004019",
            "output": "[1]"
        },
        {
            "id": "006928",
            "output": "[1]"
        },
        {
            "id": "003595",
            "output": "[1]"
        },
        {
            "id": "00343",
            "output": "[1]"
        },
        {
            "id": "004170",
            "output": "[1]"
        },
        {
            "id": "002724",
            "output": "[1]"
        },
        {
            "id": "006318",
            "output": "[1]"
        },
        {
            "id": "005001",
            "output": "[1]"
        },
        {
            "id": "007948",
            "output": "[1]"
        },
        {
            "id": "004631",
            "output": "[1]"
        },
        {
            "id": "001431",
            "output": "[1]"
        },
        {
            "id": "001363",
            "output": "[1]"
        },
        {
            "id": "005474",
            "output": "[1]"
        },
        {
            "id": "002515",
            "output": "[1]"
        },
        {
            "id": "001988",
            "output": "[1]"
        },
        {
            "id": "009091",
            "output": "[1]"
        },
        {
            "id": "001281",
            "output": "[1]"
        },
        {
            "id": "008829",
            "output": "[1]"
        },
        {
            "id": "005092",
            "output": "[1]"
        },
        {
            "id": "009033",
            "output": "[1]"
        },
        {
            "id": "008039",
            "output": "[1]"
        },
        {
            "id": "002819",
            "output": "[1]"
        },
        {
            "id": "004438",
            "output": "[1]"
        },
        {
            "id": "00803",
            "output": "[1]"
        },
        {
            "id": "003483",
            "output": "[1]"
        },
        {
            "id": "008935",
            "output": "[1]"
        },
        {
            "id": "00925",
            "output": "[1]"
        },
        {
            "id": "002319",
            "output": "[1]"
        },
        {
            "id": "00416",
            "output": "[1]"
        },
        {
            "id": "008241",
            "output": "[1]"
        },
        {
            "id": "006523",
            "output": "[1]"
        },
        {
            "id": "005629",
            "output": "[1]"
        },
        {
            "id": "004399",
            "output": "[1]"
        },
        {
            "id": "002473",
            "output": "[1]"
        },
        {
            "id": "005602",
            "output": "[1]"
        },
        {
            "id": "006690",
            "output": "[1]"
        },
        {
            "id": "007592",
            "output": "[1]"
        },
        {
            "id": "001487",
            "output": "[1]"
        },
        {
            "id": "005987",
            "output": "[1]"
        },
        {
            "id": "006479",
            "output": "[1]"
        },
        {
            "id": "005550",
            "output": "[1]"
        },
        {
            "id": "006947",
            "output": "[1]"
        },
        {
            "id": "004897",
            "output": "[1]"
        },
        {
            "id": "009215",
            "output": "[1]"
        },
        {
            "id": "006219",
            "output": "[1]"
        },
        {
            "id": "006007",
            "output": "[1]"
        },
        {
            "id": "00122",
            "output": "[1]"
        },
        {
            "id": "001319",
            "output": "[1]"
        },
        {
            "id": "005755",
            "output": "[1]"
        },
        {
            "id": "007322",
            "output": "[1]"
        },
        {
            "id": "001324",
            "output": "[1]"
        },
        {
            "id": "006084",
            "output": "[1]"
        },
        {
            "id": "001422",
            "output": "[1]"
        },
        {
            "id": "007293",
            "output": "[1]"
        },
        {
            "id": "007865",
            "output": "[1]"
        },
        {
            "id": "005950",
            "output": "[1]"
        },
        {
            "id": "00633",
            "output": "[1]"
        },
        {
            "id": "002655",
            "output": "[1]"
        },
        {
            "id": "002566",
            "output": "[1]"
        },
        {
            "id": "004423",
            "output": "[1]"
        },
        {
            "id": "007458",
            "output": "[1]"
        },
        {
            "id": "005527",
            "output": "[1]"
        },
        {
            "id": "009613",
            "output": "[1]"
        },
        {
            "id": "006749",
            "output": "[1]"
        },
        {
            "id": "001303",
            "output": "[1]"
        },
        {
            "id": "009477",
            "output": "[1]"
        },
        {
            "id": "00548",
            "output": "[1]"
        },
        {
            "id": "003164",
            "output": "[1]"
        },
        {
            "id": "006089",
            "output": "[1]"
        },
        {
            "id": "003709",
            "output": "[1]"
        },
        {
            "id": "00220",
            "output": "[1]"
        },
        {
            "id": "002801",
            "output": "[1]"
        },
        {
            "id": "002279",
            "output": "[1]"
        },
        {
            "id": "007596",
            "output": "[2]"
        },
        {
            "id": "005794",
            "output": "[2]"
        },
        {
            "id": "001481",
            "output": "[2]"
        },
        {
            "id": "008503",
            "output": "[2]"
        },
        {
            "id": "002119",
            "output": "[2]"
        },
        {
            "id": "003152",
            "output": "[2]"
        },
        {
            "id": "008529",
            "output": "[2]"
        },
        {
            "id": "007498",
            "output": "[2]"
        },
        {
            "id": "004165",
            "output": "[2]"
        },
        {
            "id": "005133",
            "output": "[2]"
        },
        {
            "id": "009483",
            "output": "[2]"
        },
        {
            "id": "006978",
            "output": "[2]"
        },
        {
            "id": "007026",
            "output": "[2]"
        },
        {
            "id": "006440",
            "output": "[2]"
        },
        {
            "id": "009564",
            "output": "[2]"
        },
        {
            "id": "008980",
            "output": "[2]"
        },
        {
            "id": "002952",
            "output": "[2]"
        },
        {
            "id": "004410",
            "output": "[2]"
        },
        {
            "id": "006226",
            "output": "[2]"
        },
        {
            "id": "002356",
            "output": "[2]"
        },
        {
            "id": "006352",
            "output": "[2]"
        },
        {
            "id": "008789",
            "output": "[2]"
        },
        {
            "id": "003035",
            "output": "[2]"
        },
        {
            "id": "003631",
            "output": "[2]"
        },
        {
            "id": "004463",
            "output": "[2]"
        },
        {
            "id": "003806",
            "output": "[2]"
        },
        {
            "id": "006309",
            "output": "[2]"
        },
        {
            "id": "00514",
            "output": "[2]"
        },
        {
            "id": "007604",
            "output": "[2]"
        },
        {
            "id": "002829",
            "output": "[2]"
        },
        {
            "id": "006101",
            "output": "[2]"
        },
        {
            "id": "004199",
            "output": "[2]"
        },
        {
            "id": "005984",
            "output": "[2]"
        },
        {
            "id": "005575",
            "output": "[2]"
        },
        {
            "id": "005111",
            "output": "[2]"
        },
        {
            "id": "001632",
            "output": "[2]"
        },
        {
            "id": "0071",
            "output": "[2]"
        },
        {
            "id": "001097",
            "output": "[2]"
        },
        {
            "id": "003792",
            "output": "[2]"
        },
        {
            "id": "002534",
            "output": "[2]"
        },
        {
            "id": "004787",
            "output": "[2]"
        },
        {
            "id": "004665",
            "output": "[2]"
        },
        {
            "id": "005089",
            "output": "[2]"
        },
        {
            "id": "001354",
            "output": "[2]"
        },
        {
            "id": "004928",
            "output": "[2]"
        },
        {
            "id": "009229",
            "output": "[2]"
        },
        {
            "id": "001735",
            "output": "[2]"
        },
        {
            "id": "00153",
            "output": "[2]"
        },
        {
            "id": "003343",
            "output": "[2]"
        },
        {
            "id": "006962",
            "output": "[2]"
        },
        {
            "id": "008405",
            "output": "[2]"
        },
        {
            "id": "001114",
            "output": "[2]"
        },
        {
            "id": "00294",
            "output": "[2]"
        },
        {
            "id": "003067",
            "output": "[2]"
        },
        {
            "id": "006101",
            "output": "[2]"
        },
        {
            "id": "008953",
            "output": "[2]"
        },
        {
            "id": "003256",
            "output": "[2]"
        },
        {
            "id": "007635",
            "output": "[2]"
        },
        {
            "id": "001297",
            "output": "[2]"
        },
        {
            "id": "006282",
            "output": "[2]"
        },
        {
            "id": "002464",
            "output": "[2]"
        },
        {
            "id": "007460",
            "output": "[2]"
        },
        {
            "id": "008868",
            "output": "[2]"
        },
        {
            "id": "004373",
            "output": "[2]"
        },
        {
            "id": "006755",
            "output": "[2]"
        },
        {
            "id": "003494",
            "output": "[2]"
        },
        {
            "id": "008297",
            "output": "[2]"
        },
        {
            "id": "004057",
            "output": "[2]"
        },
        {
            "id": "005717",
            "output": "[2]"
        },
        {
            "id": "009548",
            "output": "[2]"
        },
        {
            "id": "005469",
            "output": "[2]"
        },
        {
            "id": "004491",
            "output": "[2]"
        },
        {
            "id": "00984",
            "output": "[2]"
        },
        {
            "id": "009223",
            "output": "[2]"
        },
        {
            "id": "005176",
            "output": "[2]"
        },
        {
            "id": "006877",
            "output": "[2]"
        },
        {
            "id": "006429",
            "output": "[2]"
        },
        {
            "id": "002361",
            "output": "[2]"
        },
        {
            "id": "006243",
            "output": "[2]"
        },
        {
            "id": "00989",
            "output": "[2]"
        },
        {
            "id": "00569",
            "output": "[2]"
        },
        {
            "id": "008222",
            "output": "[2]"
        },
        {
            "id": "005869",
            "output": "[2]"
        },
        {
            "id": "002987",
            "output": "[2]"
        },
        {
            "id": "005189",
            "output": "[2]"
        },
        {
            "id": "005470",
            "output": "[2]"
        },
        {
            "id": "006676",
            "output": "[2]"
        },
        {
            "id": "002",
            "output": "[2]"
        },
        {
            "id": "001484",
            "output": "[2]"
        },
        {
            "id": "00964",
            "output": "[2]"
        },
        {
            "id": "007388",
            "output": "[2]"
        },
        {
            "id": "004488",
            "output": "[2]"
        },
        {
            "id": "001978",
            "output": "[2]"
        },
        {
            "id": "003697",
            "output": "[2]"
        },
        {
            "id": "006587",
            "output": "[2]"
        },
        {
            "id": "004571",
            "output": "[2]"
        },
        {
            "id": "005364",
            "output": "[2]"
        },
        {
            "id": "009100",
            "output": "[2]"
        },
        {
            "id": "003948",
            "output": "[2]"
        },
        {
            "id": "001059",
            "output": "[2]"
        },
        {
            "id": "001098",
            "output": "[2]"
        },
        {
            "id": "007108",
            "output": "[2]"
        },
        {
            "id": "003085",
            "output": "[2]"
        },
        {
            "id": "001171",
            "output": "[2]"
        },
        {
            "id": "007624",
            "output": "[2]"
        },
        {
            "id": "008659",
            "output": "[2]"
        },
        {
            "id": "001050",
            "output": "[2]"
        },
        {
            "id": "006042",
            "output": "[2]"
        },
        {
            "id": "007255",
            "output": "[2]"
        },
        {
            "id": "002431",
            "output": "[2]"
        },
        {
            "id": "008186",
            "output": "[2]"
        },
        {
            "id": "006731",
            "output": "[2]"
        },
        {
            "id": "004406",
            "output": "[2]"
        },
        {
            "id": "001672",
            "output": "[2]"
        },
        {
            "id": "002538",
            "output": "[2]"
        },
        {
            "id": "008122",
            "output": "[2]"
        },
        {
            "id": "001700",
            "output": "[2]"
        },
        {
            "id": "006918",
            "output": "[2]"
        },
        {
            "id": "005590",
            "output": "[2]"
        },
        {
            "id": "005495",
            "output": "[2]"
        }
    ]
}